dj_health_checker/__init__.py
dj_health_checker/admin.py
dj_health_checker/apps.py
dj_health_checker/models.py
dj_health_checker/tests.py
dj_health_checker/urls.py
dj_health_checker/utils.py
dj_health_checker/views.py
dj_health_checker/management/__init__.py
dj_health_checker/management/commands/__init__.py
dj_health_checker/management/commands/cleanup_health_data.py
dj_health_checker/management/commands/run_health_checks.py
dj_health_checker/migrations/0001_initial.py
dj_health_checker/migrations/__init__.py
dj_health_checker-1.0.0.dist-info/licenses/LICENSE
dj_health_checker-1.0.0.dist-info/METADATA
dj_health_checker-1.0.0.dist-info/WHEEL
dj_health_checker-1.0.0.dist-info/top_level.txt
dj_health_checker-1.0.0.dist-info/RECORD
